READPY/__init__.py
READPY/CLIENT/__init__.py
READPY/CLIENT/client.py
READPY/SERVER/__init__.py
READPY/SERVER/server.py
readpy_P_Y_R_O_B_O_T-1.0.3.dist-info/LICENSE
readpy_P_Y_R_O_B_O_T-1.0.3.dist-info/METADATA
readpy_P_Y_R_O_B_O_T-1.0.3.dist-info/WHEEL
readpy_P_Y_R_O_B_O_T-1.0.3.dist-info/top_level.txt
readpy_P_Y_R_O_B_O_T-1.0.3.dist-info/RECORD
