Metadata-Version: 2.1
Name: readpy-P-Y-R-O-B-O-T
Version: 1.0.3
Summary: A MINI AND EASY TO USE REDIS SERVER
Author-email: KUSHAL <NONE@NONE.com>
License: GNU GENERAL PUBLIC LICENSE
Project-URL: Homepage, https://github.com/P-Y-R-O-B-O-T/READPY
Keywords: redis,memory,communication,RAM,RAM server,memory server,shared memory,network memory,shared ram,networked memory,distributed memory,multithreaded,distributed RAM
Requires-Python: >=3.10
License-File: LICENSE
Requires-Dist: cypher-protocol-P-Y-R-O-B-O-T
